generic_response/__init__.py
generic_response/response.py
solugen_generic_flask_response-0.1.0.dist-info/LICENSE
solugen_generic_flask_response-0.1.0.dist-info/METADATA
solugen_generic_flask_response-0.1.0.dist-info/WHEEL
solugen_generic_flask_response-0.1.0.dist-info/top_level.txt
solugen_generic_flask_response-0.1.0.dist-info/RECORD
